arxiv_tool/__init__.py
arxiv_tool/__main__.py
arxiv_tool/arxiv_tool.py
arxiv_tool-0.0.1.dist-info/METADATA
arxiv_tool-0.0.1.dist-info/WHEEL
arxiv_tool-0.0.1.dist-info/entry_points.txt
arxiv_tool-0.0.1.dist-info/licenses/LICENSE
arxiv_tool-0.0.1.dist-info/RECORD
