Metadata-Version: 2.3
Name: arxiv_tool
Version: 0.0.1
Summary: Prepare your arXiv submissions
Project-URL: Homepage, https://github.com/willGuimont/arxiv_tool
Project-URL: Issues, https://github.com/willGuimont/arxiv_tool/issues
Author-email: William Guimont-Martin <william.guimont-martin@norlab.ulaval.ca>, Damien LaRocque <phicoltan@gmail.com>
License: MIT License
License-File: LICENSE
Classifier: License :: OSI Approved :: MIT License
Classifier: Operating System :: OS Independent
Classifier: Programming Language :: Python :: 3
Requires-Python: >=3.8
Requires-Dist: arxiv-collector
